{
  "slug": "qpc",
  "extension": "qpc",
  "name": "What are QPC files and how to open them",
  "summary": "Having problems opening a QPC file?",
  "programs": {
    "windows": [
      {
        "name": "KaleidaGraph",
        "url": "https://file.org/free-download/kaleidagraph"
      },
      {
        "name": "AgileLoad",
        "url": "https://file.org/free-download/agileload"
      }
    ]
  },
  "last_updated": "2025-09-22T06:55:36.027Z",
  "sources": [
    {
      "url": "file.org",
      "retrieved_at": "2025-09-22T06:55:36.027Z"
    }
  ]
}