{
  "slug": "epa",
  "extension": "epa",
  "name": "What are EPA files and how to open them",
  "summary": "Having problems opening an EPA file?",
  "programs": {
    "unspecified": [
      {
        "name": "Award BIOS Logo Bitmap",
        "url": "#awardbioslogobitmap"
      },
      {
        "name": "Pajamas Adventure System Bitmap",
        "url": "#pajamasadventuresystembitmap"
      },
      {
        "name": "Update info",
        "url": "javascript:{}"
      },
      {
        "name": "Upload example file",
        "url": "javascript:{}"
      },
      {
        "name": "Suggest a program",
        "url": "javascript:{}"
      },
      {
        "name": "HOME",
        "url": "/"
      }
    ]
  },
  "last_updated": "2025-09-22T06:29:00.659Z",
  "sources": [
    {
      "url": "file.org",
      "retrieved_at": "2025-09-22T06:29:00.659Z"
    }
  ],
  "category": "other",
  "related": [],
  "containers": []
}