{
  "slug": "kadereplay",
  "extension": "kadereplay",
  "name": "Kade Engine Replay",
  "summary": "A KADEREPLAY file is a level replay file created by the Kade Engine mod for Friday Night Funkin', a rhythm game similar to Dance Dance Revolution. It contains a plain text record of how a player completed a Friday Night Funkin' level. Using the Kade Engine, players can load KADEREPLAY files in Friday Night Funkin' and watch a replay of their previous gameplay.",
  "programs": {
    "unspecified": [
      {
        "name": "File Types",
        "url": "/filetypes/"
      },
      {
        "name": "Software",
        "url": "/apps/"
      },
      {
        "name": "Help Center",
        "url": "/help/"
      },
      {
        "name": "Random Extension",
        "url": "/random"
      },
      {
        "name": "More Information",
        "url": "#kade_engine_replay_moreinfo"
      },
      {
        "name": "How to Open",
        "url": "#kade_engine_replay_open"
      }
    ]
  },
  "last_updated": "2025-09-22T06:28:54.527Z",
  "sources": [
    {
      "url": "file.org",
      "retrieved_at": "2025-09-22T06:28:54.527Z"
    }
  ],
  "category": "other",
  "related": [],
  "containers": []
}