{
  "slug": "plasmoid",
  "extension": "plasmoid",
  "name": "Plasma Widget",
  "summary": "A PLASMOID file contains a widget used by Plasma, an open source desktop environment for various Linux distributions. It is used to distribute a small program, such as a customized clock, calendar, weather report, or email organizer.",
  "programs": {
    "unspecified": [
      {
        "name": "File Types",
        "url": "/filetypes/"
      },
      {
        "name": "Software",
        "url": "/apps/"
      },
      {
        "name": "Help Center",
        "url": "/help/"
      },
      {
        "name": "Random Extension",
        "url": "/random"
      },
      {
        "name": "More Information",
        "url": "#plasma_widget_moreinfo"
      },
      {
        "name": "Program List",
        "url": "#plasma_widget_apps"
      }
    ]
  },
  "last_updated": "2025-09-22T06:28:47.694Z",
  "sources": [
    {
      "url": "file.org",
      "retrieved_at": "2025-09-22T06:28:47.694Z"
    }
  ],
  "category": "other",
  "related": [],
  "containers": []
}