{
  "slug": "vsqx",
  "extension": "vsqx",
  "name": "VOCALOID3 Project File",
  "summary": "A VSQX file is a project file created by VOCALOID3, an application used to make and arrange synthesized vocals. It stores musical notes, lyrics, and vocal data for each note that are emulated by synthesized voices in VOCALOID3.",
  "programs": {
    "unspecified": [
      {
        "name": "File Types",
        "url": "/filetypes/"
      },
      {
        "name": "Software",
        "url": "/apps/"
      },
      {
        "name": "Help Center",
        "url": "/help/"
      },
      {
        "name": "Random Extension",
        "url": "/random"
      },
      {
        "name": "More Information",
        "url": "#vocaloid3_project_file_moreinfo"
      },
      {
        "name": "Program List",
        "url": "#vocaloid3_project_file_apps"
      }
    ]
  },
  "last_updated": "2025-09-22T06:28:58.329Z",
  "sources": [
    {
      "url": "file.org",
      "retrieved_at": "2025-09-22T06:28:58.329Z"
    }
  ],
  "category": "other",
  "related": [],
  "containers": []
}