{
  "slug": "xmv",
  "extension": "xmv",
  "name": "Xbox Media Video File",
  "summary": "Video file used by some games for the Xbox console system; uses a format developed by Microsoft specifically for playback on the Xbox; typically converted from a .WMV file to the XMV format using xmvtool, a program included with the Xbox software development kit provided by Microsoft.",
  "programs": {
    "unspecified": [
      {
        "name": "File Types",
        "url": "/filetypes/"
      },
      {
        "name": "Software",
        "url": "/apps/"
      },
      {
        "name": "Help Center",
        "url": "/help/"
      },
      {
        "name": "Random Extension",
        "url": "/random"
      },
      {
        "name": "More Information",
        "url": "#xbox_media_video_file_moreinfo"
      },
      {
        "name": "Program List",
        "url": "#xbox_media_video_file_apps"
      }
    ]
  },
  "last_updated": "2025-09-22T06:29:02.320Z",
  "sources": [
    {
      "url": "file.org",
      "retrieved_at": "2025-09-22T06:29:02.320Z"
    }
  ],
  "category": "other",
  "related": [],
  "containers": []
}