{"slug":"appxbundle","extension":"appxbundle","name":"Windows App Bundle","category":"windows-app-bundle","summary":"","developer_org":"microsoft","developer_name":"Microsoft","more_information":{"description":["The different architectures in APPXBUNDLE files allow the appropriate version of the app to be deployed to a matching computer's architecture. For example, a 32-bit system may receive the x86 version of the app while a 64-bit system receives the x64 version. By including multiple architectures into an APPXBUNDLE file, developers can support a wide range of devices with a single installer package.","AppX bundles are created by Visual Studio, Microsoft's primary Windows development IDE. Developers can upload bundles to the Microsoft Store, or make them available for sideloading, a process that allows users to manually install apps.","NOTE: Single app packages are saved as .APPX files."]},"updated_at":"2025-08-09","sources":[{"url":"appxbundle.html","retrieved_at":"2025-08-09"}]}