{"slug":"ms-one-stub","extension":"ms-one-stub","name":"Microsoft OneNote Stub","category":"microsoft-onenote-stub","summary":"","developer_org":"microsoft","developer_name":"Microsoft","more_information":{"description":["Microsoft OneNote is a digital notebook application that allows users to take notes on their computer and share those notes with others. Microsoft OneDrive is a cloud storage application that, among other things, allows users to upload, access, and share their OneNote notebooks over the Internet.","When a OneDrive user creates or opens a new cloud-based notebook, OneDrive stores some files associated with that notebook on the user's PC. One of these files is an MS-ONE-STUB file, which is a pointer file that references and can be used to open the cloud-based notebook."]},"updated_at":"2025-08-09","sources":[{"url":"ms-one-stub.html","retrieved_at":"2025-08-09"}]}