{"slug":"searchconnector-ms","extension":"searchconnector-ms","name":"Windows Search Connector File","category":"windows-search-connector-file","summary":"","developer_org":"microsoft","developer_name":"Microsoft","more_information":{"description":["Search Connectors are installed on the user computer using an OpenSearch Description .OSDX file, which contains information about the remote service. After the OSDX file is opened, the SEARCHCONNECTOR-MS file is installed to the [user]\\​Searches\\​ directory and appears as a folder with a magnifying glass graphic. When you open the file, Windows opens an Explorer window with the contents of the remote location.","NOTE: Search Connector files do not display the \".searchconnector-ms\" extension."]},"updated_at":"2025-08-09","sources":[{"url":"searchconnector-ms.html","retrieved_at":"2025-08-09"}]}