{
  "slug": "mato",
  "extension": "mato",
  "name": "Atomic Combat Saved Game",
  "category": "atomic-combat-saved-game",
  "summary": "",
  "developer_org": "mojiferous-industries",
  "developer_name": "Mojiferous Industries",
  "more_information": {
    "description": [
      "MATO files are only created by Atomic Combat 1.x since Atomic Combat 2 does not include a Save function.",
      "NOTE: Mojiferous Atomic Combat is discontinued."
    ]
  },
  "updated_at": "2025-08-09",
  "sources": [
    {
      "url": "mato.html",
      "retrieved_at": "2025-08-09"
    }
  ]
}