{
  "slug": "8svx",
  "extension": "8svx",
  "name": "Amiga 8-Bit Sound File",
  "category": "amiga-8-bit-sound-file",
  "developer_org": "n-a",
  "popularity": {
    "rating": 3.3,
    "votes": 13,
    "source": "fileinfo"
  },
  "summary": "Audio file used by the older Amiga personal computers; stores recorded audio in the 8-bit quality 8SVX format, which is a derivative format of the .IFF specification; supports mono and stereo sound.",
  "standards": [],
  "mime_types": [
    "n/a"
  ],
  "related_types": [],
  "how_to": {
    "save_as": [],
    "open": [
      {
        "mode": "native",
        "note": "Open with an associated app listed below.",
        "apps": []
      }
    ],
    "convert": []
  },
  "programs_by_platform": {
    "windows": [
      {
        "software": "file-viewer-plus",
        "display_name": "File Viewer Plus"
      },
      {
        "software": "xmplay",
        "display_name": "XMPlay"
      },
      {
        "software": "deliplayer",
        "display_name": "DeliPlayer"
      },
      {
        "software": "cloanto-amiga-forever",
        "display_name": "Cloanto Amiga Forever"
      },
      {
        "software": "audacity",
        "display_name": "Audacity"
      },
      {
        "software": "sox",
        "display_name": "SoX"
      },
      {
        "software": "filehelper.com",
        "display_name": "FileHelper.com"
      }
    ],
    "macos": [
      {
        "software": "cloanto-amiga-forever",
        "display_name": "Cloanto Amiga Forever"
      },
      {
        "software": "audacity",
        "display_name": "Audacity"
      },
      {
        "software": "sox",
        "display_name": "SoX"
      }
    ],
    "linux": [
      {
        "software": "audacity",
        "display_name": "Audacity"
      },
      {
        "software": "sox",
        "display_name": "SoX"
      }
    ],
    "web": [
      {
        "software": "filehelper.com",
        "display_name": "FileHelper.com"
      }
    ]
  },
  "images": [],
  "verification": {
    "verified_by": "fileinfo",
    "verification_note": "Parsed from downloaded FileInfo page."
  },
  "updated_at": "2014-07-30",
  "sources": [
    {
      "url": "8svx.html",
      "retrieved_at": "2025-08-09"
    }
  ]
}