{
  "slug": "art",
  "extension": "art",
  "name": "ArtCAM Model",
  "category": "1.-artcam-model",
  "developer_org": "delcam",
  "popularity": {
    "rating": 3.5,
    "votes": 51,
    "source": "fileinfo"
  },
  "summary": "CAD model created by ArtCAM, a CNC (computer numerical control) program used for artistic design and manufacturing; saves a 2D or 3D model as well as instructions for a machine to cut or engrave the design; used for signs, woodworking, engraving, and jewelry.",
  "standards": [],
  "mime_types": [
    "n/a"
  ],
  "related_types": [],
  "how_to": {
    "save_as": [],
    "open": [
      {
        "mode": "native",
        "note": "Open with an associated app listed below.",
        "apps": []
      }
    ],
    "convert": []
  },
  "programs_by_platform": {
    "windows": [
      {
        "software": "delcam-artcam",
        "display_name": "Delcam ArtCAM"
      },
      {
        "software": "aol",
        "display_name": "AOL"
      },
      {
        "software": "acd-systems-acdsee-photo-studio",
        "display_name": "ACD Systems ACDSee Photo Studio"
      },
      {
        "software": "bernina-artlink",
        "display_name": "BERNINA ARTlink"
      },
      {
        "software": "adobe-illustrator-2025",
        "display_name": "Adobe Illustrator 2025"
      },
      {
        "software": "coreldraw-graphics-suite-2024",
        "display_name": "CorelDRAW Graphics Suite 2024"
      },
      {
        "software": "versioned-artifacts",
        "display_name": "Versioned Artifacts"
      }
    ],
    "macos": [
      {
        "software": "aol",
        "display_name": "AOL"
      },
      {
        "software": "adobe-illustrator-2025",
        "display_name": "Adobe Illustrator 2025"
      }
    ],
    "web": [
      {
        "software": "visual-paradigm-online",
        "display_name": "Visual Paradigm Online"
      }
    ]
  },
  "images": [],
  "verification": {
    "verified_by": "fileinfo",
    "verification_note": "Parsed from downloaded FileInfo page."
  },
  "updated_at": "2020-07-17",
  "sources": [
    {
      "url": "art.html",
      "retrieved_at": "2025-08-09"
    }
  ]
}