{
  "slug": "as2proj",
  "extension": "as2proj",
  "name": "FlashDevelop ActionScript 2 Project File",
  "category": "flashdevelop-actionscript-2-project-file",
  "developer_org": "flashdevelop",
  "popularity": {
    "rating": 3.6,
    "votes": 7,
    "source": "fileinfo"
  },
  "summary": "Project file created by FlashDevelop, an free and open source development IDE commonly used for Flash programming; saved in an XML format and contains build settings, references to project source code files, and output .SWF options.",
  "standards": [],
  "mime_types": [],
  "related_types": [],
  "how_to": {
    "save_as": [],
    "open": [
      {
        "mode": "native",
        "note": "Open with an associated app listed below.",
        "apps": []
      }
    ],
    "convert": []
  },
  "programs_by_platform": {
    "windows": [
      {
        "software": "flashdevelop",
        "display_name": "FlashDevelop"
      }
    ],
    "macos": [
      {
        "software": "flashdevelop",
        "display_name": "FlashDevelop"
      }
    ],
    "linux": [
      {
        "software": "flashdevelop",
        "display_name": "FlashDevelop"
      }
    ]
  },
  "images": [],
  "verification": {
    "verified_by": "fileinfo",
    "verification_note": "Parsed from downloaded FileInfo page."
  },
  "updated_at": "2011-03-10",
  "sources": [
    {
      "url": "as2proj.html",
      "retrieved_at": "2025-08-09"
    }
  ]
}