{
  "slug": "ascii",
  "extension": "ascii",
  "name": "ASCII Text File",
  "category": "ascii-text-file",
  "developer_org": "american-national-standards-institute",
  "popularity": {
    "rating": 2.8,
    "votes": 16,
    "source": "fileinfo"
  },
  "summary": "An ASCII file is a plain text file that uses ASCII character encoding. You can open and edit an ASCII file in most any text editor or word processor. ASCII files are more commonly saved with the .TXT or .ASC extension.",
  "standards": [],
  "mime_types": [],
  "related_types": [],
  "how_to": {
    "save_as": [],
    "open": [
      {
        "mode": "native",
        "note": "Open with an associated app listed below.",
        "apps": []
      }
    ],
    "convert": []
  },
  "programs_by_platform": {
    "windows": [
      {
        "software": "microsoft-notepad",
        "display_name": "Microsoft Notepad"
      },
      {
        "software": "microsoft-wordpad",
        "display_name": "Microsoft WordPad"
      },
      {
        "software": "microsoft-word-365",
        "display_name": "Microsoft Word 365"
      },
      {
        "software": "apache-openoffice",
        "display_name": "Apache OpenOffice"
      },
      {
        "software": "github-atom",
        "display_name": "GitHub Atom",
        "status": "discontinued"
      },
      {
        "software": "text-editor",
        "display_name": "text editor"
      },
      {
        "software": "apple-textedit",
        "display_name": "Apple TextEdit"
      },
      {
        "software": "apple-pages",
        "display_name": "Apple Pages"
      }
    ],
    "macos": [
      {
        "software": "apple-textedit",
        "display_name": "Apple TextEdit"
      },
      {
        "software": "apple-pages",
        "display_name": "Apple Pages"
      },
      {
        "software": "microsoft-word-365",
        "display_name": "Microsoft Word 365"
      },
      {
        "software": "apache-openoffice",
        "display_name": "Apache OpenOffice"
      },
      {
        "software": "github-atom",
        "display_name": "GitHub Atom",
        "status": "discontinued"
      },
      {
        "software": "text-editor",
        "display_name": "text editor"
      }
    ],
    "linux": [
      {
        "software": "apache-openoffice",
        "display_name": "Apache OpenOffice"
      },
      {
        "software": "github-atom",
        "display_name": "GitHub Atom",
        "status": "discontinued"
      },
      {
        "software": "text-editor",
        "display_name": "text editor"
      }
    ]
  },
  "images": [
    {
      "caption": "ASCII file open in Microsoft WordPad",
      "alt": "ASCII file open in Microsoft WordPad",
      "source_url": "https://fileinfo.com/img/ss/md/ascii_931.png"
    }
  ],
  "verification": {
    "verified_by": "fileinfo",
    "verification_note": "Parsed from downloaded FileInfo page."
  },
  "updated_at": "2022-06-29",
  "sources": [
    {
      "url": "ascii.html",
      "retrieved_at": "2025-08-09"
    }
  ]
}