{
  "slug": "blf",
  "extension": "blf",
  "name": "CLFS Base Log File",
  "category": "1.-clfs-base-log-file",
  "developer_org": "microsoft",
  "popularity": {
    "rating": 3.3,
    "votes": 33,
    "source": "fileinfo"
  },
  "summary": "Log file created by the Common Log File System (CLFS), a Microsoft Windows component used for creating transaction logs; contains metadata that is used to manage access to the log data; can be created using the CLFS ( API ); used with \"containers,\" which are associated files that hold the log data.",
  "standards": [],
  "mime_types": [],
  "related_types": [],
  "how_to": {
    "save_as": [],
    "open": [
      {
        "mode": "native",
        "note": "Open with an associated app listed below.",
        "apps": []
      }
    ],
    "convert": []
  },
  "programs_by_platform": {
    "windows": [
      {
        "software": "microsoft-common-log-file-system",
        "display_name": "Microsoft Common Log File System"
      },
      {
        "software": "designer-s-gallery-masterworks",
        "display_name": "Designer's Gallery MasterWorks"
      },
      {
        "software": "vector-informatik-canoe",
        "display_name": "Vector Informatik CANoe"
      },
      {
        "software": "vector-informatik-canalyzer",
        "display_name": "Vector Informatik CANalyzer"
      }
    ]
  },
  "images": [],
  "verification": {
    "verified_by": "fileinfo",
    "verification_note": "Parsed from downloaded FileInfo page."
  },
  "updated_at": "2011-03-10",
  "sources": [
    {
      "url": "blf.html",
      "retrieved_at": "2025-08-09"
    }
  ]
}