{
  "slug": "canvas",
  "extension": "canvas",
  "name": "Obsidian Canvas",
  "category": "obsidian-canvas",
  "developer_org": "obsidian",
  "popularity": {
    "rating": 3.5,
    "votes": 2,
    "source": "fileinfo"
  },
  "summary": "A CANVAS file is a visual workspace created by Obsidian, a note-taking and knowledge management application. It stores the layout and structure of a user's canvas, including the position of content blocks (called \"cards\") and their connections, in the plain text JSON Canvas format. CANVAS files don't directly store the content of notes or media files; instead, they reference the location of the files (e.g., .MD Note files) in the user's Obsidian \"vault\" (a folder).",
  "standards": [],
  "mime_types": [],
  "related_types": [],
  "how_to": {
    "save_as": [],
    "open": [
      {
        "mode": "native",
        "note": "Open with an associated app listed below.",
        "apps": []
      }
    ],
    "convert": []
  },
  "programs_by_platform": {
    "web": [
      {
        "software": "obsidian",
        "display_name": "Obsidian"
      },
      {
        "software": "text-editor",
        "display_name": "text editor"
      },
      {
        "software": "flowchart-fun",
        "display_name": "Flowchart Fun"
      },
      {
        "software": "kinopio",
        "display_name": "Kinopio"
      },
      {
        "software": "hi-canvas",
        "display_name": "hi-canvas"
      },
      {
        "software": "orgpad",
        "display_name": "OrgPad"
      }
    ],
    "windows": [
      {
        "software": "obsidian",
        "display_name": "Obsidian"
      },
      {
        "software": "text-editor",
        "display_name": "text editor"
      },
      {
        "software": "flowchart-fun",
        "display_name": "Flowchart Fun"
      },
      {
        "software": "kinopio",
        "display_name": "Kinopio"
      },
      {
        "software": "hi-canvas",
        "display_name": "hi-canvas"
      },
      {
        "software": "orgpad",
        "display_name": "OrgPad"
      }
    ]
  },
  "images": [
    {
      "caption": "CANVAS file open in Obsidian 1.8",
      "alt": "CANVAS file open in Obsidian 1.8",
      "source_url": "https://fileinfo.com/img/ss/md/canvas_13819.jpg"
    }
  ],
  "verification": {
    "verified_by": "fileinfo",
    "verification_note": "Parsed from downloaded FileInfo page."
  },
  "updated_at": "2025-07-09",
  "sources": [
    {
      "url": "canvas.html",
      "retrieved_at": "2025-08-09"
    }
  ]
}