{
  "slug": "h266",
  "extension": "h266",
  "name": "H.266 (VVC) Video",
  "category": "h.266-vvc-video",
  "developer_org": "jvet",
  "popularity": {
    "rating": 2.0,
    "votes": 1,
    "source": "fileinfo"
  },
  "summary": "An H266 file is a video saved using the H.266 video compression standard. The H.266 standard is also referred to as Versatile Video Coding (VVC). Therefore, you may see H266 files referred to as VVC files.",
  "standards": [],
  "mime_types": [],
  "related_types": [],
  "how_to": {
    "save_as": [],
    "open": [
      {
        "mode": "native",
        "note": "Open with an associated app listed below.",
        "apps": []
      }
    ],
    "convert": []
  },
  "programs_by_platform": {
    "windows": [
      {
        "software": "fraunhofer-vvdec",
        "display_name": "Fraunhofer VVdeC"
      },
      {
        "software": "spin-digital-vvc-media-player",
        "display_name": "Spin Digital VVC Media Player"
      },
      {
        "software": "j2-interactive-mx-player",
        "display_name": "J2 Interactive MX Player"
      }
    ],
    "linux": [
      {
        "software": "spin-digital-vvc-media-player",
        "display_name": "Spin Digital VVC Media Player"
      }
    ],
    "android": [
      {
        "software": "j2-interactive-mx-player",
        "display_name": "J2 Interactive MX Player"
      }
    ]
  },
  "images": [],
  "verification": {
    "verified_by": "fileinfo",
    "verification_note": "Parsed from downloaded FileInfo page."
  },
  "updated_at": "2022-12-08",
  "sources": [
    {
      "url": "h266.html",
      "retrieved_at": "2025-08-09"
    }
  ]
}