{
  "slug": "rmvb",
  "extension": "rmvb",
  "name": "RealMedia Variable Bit Rate File",
  "category": "realmedia-variable-bit-rate-file",
  "developer_org": "realnetworks",
  "popularity": {
    "rating": 3.8,
    "votes": 44,
    "source": "fileinfo"
  },
  "summary": "An RMVB file is a Real Media video file compressed using a variable bitrate , which is optimized for the content of the video. It is a newer variation of the standard Real Media ( .RM ) file format that allows for more efficient compression.",
  "standards": [],
  "mime_types": [
    "20/20"
  ],
  "related_types": [],
  "how_to": {
    "save_as": [],
    "open": [
      {
        "mode": "native",
        "note": "Open with an associated app listed below.",
        "apps": []
      }
    ],
    "convert": []
  },
  "programs_by_platform": {
    "windows": [
      {
        "software": "file-viewer-plus",
        "display_name": "File Viewer Plus"
      },
      {
        "software": "realnetworks-realplayer-20-20",
        "display_name": "RealNetworks RealPlayer 20/20"
      },
      {
        "software": "videolan-vlc-media-player",
        "display_name": "VideoLAN VLC media player"
      },
      {
        "software": "gretech-gom-player",
        "display_name": "GRETECH GOM Player"
      },
      {
        "software": "aiseesoft-video-converter-ultimate",
        "display_name": "Aiseesoft Video Converter Ultimate"
      },
      {
        "software": "eltima-elmedia-player",
        "display_name": "Eltima Elmedia Player"
      },
      {
        "software": "olimsoft-oplayer",
        "display_name": "olimsoft OPlayer"
      }
    ],
    "macos": [
      {
        "software": "aiseesoft-mac-video-converter-ultimate",
        "display_name": "Aiseesoft Mac Video Converter Ultimate"
      },
      {
        "software": "eltima-elmedia-player",
        "display_name": "Eltima Elmedia Player"
      }
    ],
    "linux": [
      {
        "software": "videolan-vlc-media-player",
        "display_name": "VideoLAN VLC media player"
      }
    ],
    "ios": [
      {
        "software": "olimsoft-oplayer",
        "display_name": "olimsoft OPlayer"
      }
    ]
  },
  "images": [
    {
      "caption": "RMVB file icon",
      "alt": "RMVB file icon",
      "source_url": "https://fileinfo.com/img/icons/files/256/rmvb-1030.png"
    }
  ],
  "verification": {
    "verified_by": "fileinfo",
    "verification_note": "Parsed from downloaded FileInfo page."
  },
  "updated_at": "2020-09-24",
  "sources": [
    {
      "url": "rmvb.html",
      "retrieved_at": "2025-08-09"
    }
  ]
}