{
  "slug": "sdef",
  "extension": "sdef",
  "name": "AppleScript Dictionary Document",
  "category": "applescript-dictionary-document",
  "developer_org": "apple",
  "popularity": {
    "rating": 2.5,
    "votes": 2,
    "source": "fileinfo"
  },
  "summary": "XML dictionary file created for scripts written in the AppleScript language; contains a dictionary of terms, which includes classes (nouns), properties (adjectives), commands (verbs), and parameters (adverbs); stores the terminology used to communicate with the underlying program being controlled by the script.",
  "standards": [],
  "mime_types": [],
  "related_types": [],
  "how_to": {
    "save_as": [],
    "open": [
      {
        "mode": "native",
        "note": "Open with an associated app listed below.",
        "apps": []
      }
    ],
    "convert": []
  },
  "programs_by_platform": {
    "macos": [
      {
        "software": "apple-script-editor",
        "display_name": "Apple Script Editor"
      },
      {
        "software": "apple-xcode",
        "display_name": "Apple Xcode"
      }
    ],
    "windows": [
      {
        "software": "apple-script-editor",
        "display_name": "Apple Script Editor"
      },
      {
        "software": "apple-xcode",
        "display_name": "Apple Xcode"
      }
    ]
  },
  "images": [],
  "verification": {
    "verified_by": "fileinfo",
    "verification_note": "Parsed from downloaded FileInfo page."
  },
  "updated_at": "2016-10-28",
  "sources": [
    {
      "url": "sdef.html",
      "retrieved_at": "2025-08-09"
    }
  ]
}