{
  "slug": "sys",
  "extension": "sys",
  "name": "Windows System File",
  "category": "1.-windows-system-file",
  "developer_org": "microsoft",
  "popularity": {
    "rating": 4.1,
    "votes": 969,
    "source": "fileinfo"
  },
  "summary": "An SYS file is a system file used by Microsoft DOS and Windows operating systems . It contains system settings and variables, and functions that are used to run the operating system. SYS files are commonly used to store device drivers and other core Windows functions.",
  "standards": [],
  "mime_types": [],
  "related_types": [],
  "how_to": {
    "save_as": [],
    "open": [
      {
        "mode": "native",
        "note": "Open with an associated app listed below.",
        "apps": []
      }
    ],
    "convert": []
  },
  "programs_by_platform": {
    "windows": [
      {
        "software": "microsoft-windows",
        "display_name": "Microsoft Windows"
      },
      {
        "software": "parallels-desktop-for-mac-with-windows-installed",
        "display_name": "Parallels Desktop for Mac with Windows installed"
      },
      {
        "software": "p2kman",
        "display_name": "P2KMan"
      },
      {
        "software": "discontinued",
        "display_name": "Discontinued",
        "status": "discontinued"
      }
    ]
  },
  "images": [
    {
      "caption": "SYS file icon",
      "alt": "SYS file icon",
      "source_url": "https://fileinfo.com/img/icons/files/256/sys-104.png"
    }
  ],
  "verification": {
    "verified_by": "fileinfo",
    "verification_note": "Parsed from downloaded FileInfo page."
  },
  "updated_at": "2020-12-31",
  "sources": [
    {
      "url": "sys.html",
      "retrieved_at": "2025-08-09"
    }
  ]
}