{
  "slug": "tsv",
  "extension": "tsv",
  "name": "Tab-Separated Values File",
  "category": "1.-tab-separated-values-file",
  "developer_org": "n-a",
  "popularity": {
    "rating": 3.6,
    "votes": 107,
    "source": "fileinfo"
  },
  "summary": "A TSV file contains a plain text data table saved in the tab-separated values format. The table is divided into columns, separated by tabs, and rows, separated by line breaks. Commonly, users open TSV files with Microsoft Excel , Google Sheets , and other spreadsheet applications, to view the data they contain as a spreadsheet.",
  "standards": [],
  "mime_types": [
    "n/a"
  ],
  "related_types": [],
  "how_to": {
    "save_as": [],
    "open": [
      {
        "mode": "native",
        "note": "Open with an associated app listed below.",
        "apps": []
      }
    ],
    "convert": []
  },
  "programs_by_platform": {
    "windows": [
      {
        "software": "file-viewer-plus",
        "display_name": "File Viewer Plus"
      },
      {
        "software": "microsoft-excel-365",
        "display_name": "Microsoft Excel 365"
      },
      {
        "software": "libreoffice",
        "display_name": "LibreOffice"
      },
      {
        "software": "openoffice-calc",
        "display_name": "OpenOffice Calc"
      },
      {
        "software": "microsoft-notepad",
        "display_name": "Microsoft Notepad"
      },
      {
        "software": "text-editor",
        "display_name": "text editor"
      },
      {
        "software": "apple-numbers",
        "display_name": "Apple Numbers"
      },
      {
        "software": "apple-textedit",
        "display_name": "Apple TextEdit"
      },
      {
        "software": "filehelper.com",
        "display_name": "FileHelper.com"
      },
      {
        "software": "google-sheets",
        "display_name": "Google Sheets"
      },
      {
        "software": "apple-files",
        "display_name": "Apple Files"
      },
      {
        "software": ".mp4",
        "display_name": ".MP4"
      },
      {
        "software": ".ts",
        "display_name": ".TS"
      },
      {
        "software": ".asf",
        "display_name": ".ASF"
      },
      {
        "software": "supported-by-the-tv-receiver-that-created-the-tsv-file",
        "display_name": "Supported by the TV receiver that created the TSV file"
      },
      {
        "software": "codec-guide-k-lite-codec-pack",
        "display_name": "Codec Guide K-Lite Codec Pack"
      },
      {
        "software": "videolan-vlc-media-player",
        "display_name": "VideoLAN VLC media player"
      },
      {
        "software": "aiseesoft-free-video-converter",
        "display_name": "Aiseesoft Free Video Converter",
        "pricing": "free"
      }
    ],
    "android": [
      {
        "software": "file-viewer-for-android",
        "display_name": "File Viewer for Android"
      },
      {
        "software": "google-sheets",
        "display_name": "Google Sheets"
      }
    ],
    "macos": [
      {
        "software": "apple-numbers",
        "display_name": "Apple Numbers"
      },
      {
        "software": "microsoft-excel-365",
        "display_name": "Microsoft Excel 365"
      },
      {
        "software": "libreoffice",
        "display_name": "LibreOffice"
      },
      {
        "software": "openoffice-calc",
        "display_name": "OpenOffice Calc"
      },
      {
        "software": "apple-textedit",
        "display_name": "Apple TextEdit"
      },
      {
        "software": "text-editor",
        "display_name": "text editor"
      },
      {
        "software": "supported-by-the-tv-receiver-that-created-the-tsv-file",
        "display_name": "Supported by the TV receiver that created the TSV file"
      },
      {
        "software": "aiseesoft-free-video-converter",
        "display_name": "Aiseesoft Free Video Converter",
        "pricing": "free"
      },
      {
        "software": "videolan-vlc-media-player",
        "display_name": "VideoLAN VLC media player"
      }
    ],
    "linux": [
      {
        "software": "libreoffice",
        "display_name": "LibreOffice"
      },
      {
        "software": "openoffice-calc",
        "display_name": "OpenOffice Calc"
      },
      {
        "software": "text-editor",
        "display_name": "text editor"
      },
      {
        "software": "supported-by-the-tv-receiver-that-created-the-tsv-file",
        "display_name": "Supported by the TV receiver that created the TSV file"
      },
      {
        "software": "videolan-vlc-media-player",
        "display_name": "VideoLAN VLC media player"
      }
    ],
    "web": [
      {
        "software": "filehelper.com",
        "display_name": "FileHelper.com"
      },
      {
        "software": "google-sheets",
        "display_name": "Google Sheets"
      },
      {
        "software": "microsoft-excel-365",
        "display_name": "Microsoft Excel 365"
      },
      {
        "software": ".webm",
        "display_name": ".WEBM"
      }
    ],
    "ios": [
      {
        "software": "apple-files",
        "display_name": "Apple Files"
      },
      {
        "software": "google-sheets",
        "display_name": "Google Sheets"
      }
    ]
  },
  "images": [
    {
      "caption": "TSV file icon",
      "alt": "TSV file icon",
      "source_url": "https://fileinfo.com/img/icons/files/256/tsv-310.png"
    },
    {
      "caption": "TSV file open in Google Sheets",
      "alt": "TSV file open in Google Sheets",
      "source_url": "https://fileinfo.com/img/ss/md/tsv_310-4.png"
    }
  ],
  "verification": {
    "verified_by": "fileinfo",
    "verification_note": "Parsed from downloaded FileInfo page."
  },
  "updated_at": "2023-06-16",
  "sources": [
    {
      "url": "tsv.html",
      "retrieved_at": "2025-08-09"
    }
  ]
}